pycaroon/hello.py
pycaroon-0.0.1.dist-info/WHEEL
pycaroon-0.0.1.dist-info/METADATA
pycaroon-0.0.1.dist-info/RECORD
